qolor_tyme/__init__.py
qolor_tyme/__main__.py
qolor_tyme/qolor_tyme.py
qolor_tyme-1.0.1.dist-info/LICENSE
qolor_tyme-1.0.1.dist-info/METADATA
qolor_tyme-1.0.1.dist-info/WHEEL
qolor_tyme-1.0.1.dist-info/top_level.txt
qolor_tyme-1.0.1.dist-info/RECORD
