Metadata-Version: 2.1
Name: qolor-tyme
Version: 1.0.1
Summary: A Toastmasters-inspired speech timer for online scrum meetings
Home-page: https://github.com/tromgy/qolor-tyme
Author: Tromgy
Author-email: tromgy@yahoo.com
License: UNKNOWN
Keywords: pyqt5 scrum toastmasters-timer
Platform: UNKNOWN
Classifier: License :: OSI Approved :: GNU General Public License v3 (GPLv3)
Classifier: Programming Language :: Python :: 3
Classifier: Programming Language :: Python :: 3.9
License-File: LICENSE
Requires-Dist: PyQt5
